jupyviv/__init__.py
jupyviv/agent/__init__.py
jupyviv/agent/kernel.py
jupyviv/handler/__init__.py
jupyviv/handler/endpoints.py
jupyviv/handler/new.py
jupyviv/handler/sync.py
jupyviv/handler/vivify.py
jupyviv/shared/deque.py
jupyviv/shared/errors.py
jupyviv/shared/lifetime.py
jupyviv/shared/logs.py
jupyviv/shared/messages.py
jupyviv/shared/utils.py
jupyviv/shared/transport/iostream.py
jupyviv/shared/transport/websocket.py
jupyviv-0.1.2.dist-info/METADATA
jupyviv-0.1.2.dist-info/WHEEL
jupyviv-0.1.2.dist-info/entry_points.txt
jupyviv-0.1.2.dist-info/licenses/LICENSE
jupyviv-0.1.2.dist-info/RECORD
