Metadata-Version: 2.4
Name: jupyviv
Version: 0.1.2
Summary: Edit and run Jupyter Notebooks with plain text editors like Neovim while live viewing them with Vivify 
Project-URL: Homepage, https://github.com/jannis-baum/Jupyviv
Author: Jannis Baum
License-Expression: GPL-3.0-or-later
License-File: LICENSE
Requires-Python: >=3.9
Requires-Dist: jupyter-client>=8.6.3
Requires-Dist: jupytext>=1.16.7
Requires-Dist: psutil>=7.0.0
Requires-Dist: requests>=2.32.3
Requires-Dist: websockets>=15.0.1
